bumpanything/__init__.py
bumpanything/__main__.py
bumpanything/file_result.py
bumpanything/git.py
bump_anything-2.3.0.dist-info/WHEEL
bump_anything-2.3.0.dist-info/entry_points.txt
bump_anything-2.3.0.dist-info/METADATA
bump_anything-2.3.0.dist-info/RECORD
