Metadata-Version: 2.4
Name: bump-anything
Version: 2.3.0
Summary: A CLI utility for bumping the version of any file type
Keywords: semver,semantic,version,versioning,bump,increment
Author: Caleb Evans
Author-email: Caleb Evans <caleb@calebevans.me>
License-Expression: MIT
Requires-Dist: semver>=3
Maintainer: Caleb Evans
Maintainer-email: Caleb Evans <caleb@calebevans.me>
Requires-Python: >=3.9
Project-URL: changelog, https://github.com/caleb531/bump-anything/releases
Project-URL: documentation, https://github.com/caleb531/bump-anything#readme
Project-URL: homepage, https://github.com/caleb531/bump-anything
Project-URL: repository, https://github.com/caleb531/bump-anything
